{
	"attributes": {
		"title": "Craete Todo App With Golang",
		"description": "Mollitia et numquam sed et facere est et repellendus ea.",
		"thumbnail": "http://placeimg.com/640/480/robot",
		"publishedAt": "2022-06-25T14:34:09.275Z",
		"label": ["golang", "echo"],
		"commentId": 15,
		"readTime": 1
	},
	"body": "Commodi aut fugit magni ipsa asperiores eum ea nulla at. Incidunt quisquam dolorem dolor dolorem. Est culpa et alias eum ipsam cumque ullam. Culpa impedit harum et deserunt sunt amet. Dicta eius perspiciatis rerum earum sequi ut. Optio culpa laboriosam hic non.\n\nFuga quaerat aliquid ad est cupiditate quis dolorem nam. Voluptate dolor ipsam. Hic ullam officiis fugiat soluta tempora. Id omnis nam non nam optio consequatur est. Sapiente iure nihil. Doloremque voluptate ipsa magni accusamus molestias nihil et nisi.\n\nNisi nisi qui provident. Occaecati qui hic voluptate distinctio unde quas molestiae et quas. Ullam qui consequatur aut recusandae qui autem et maiores modi. Delectus ducimus eos quibusdam repellendus at.\n\nEst suscipit voluptas temporibus debitis asperiores possimus et. Provident voluptatem sint rerum molestiae. Praesentium magnam a perspiciatis earum. Nulla autem non ipsa. Quia recusandae in.\n\nVel ut qui qui illum. Alias aliquam non ad et blanditiis. Voluptate animi ut qui incidunt qui enim temporibus qui aspernatur. Enim est rem id aut est amet at consequatur veniam. Porro et non eius expedita.\n\nAdipisci cupiditate porro aliquam id qui. Qui doloremque sapiente consequatur pariatur vel doloremque quisquam nobis ipsum. Vel pariatur nihil blanditiis possimus soluta provident nam et. Voluptatem vel tempore dolores sit quia iste dolores qui. Rerum quis esse voluptas quibusdam atque vitae dolores necessitatibus nisi.\n"
}
